SRW_parser/SRW_parser.py
SRW_parser/__init__.py
SRW_parser/_version.py
SRW_parser-0.1.4.dist-info/METADATA
SRW_parser-0.1.4.dist-info/RECORD
SRW_parser-0.1.4.dist-info/WHEEL
SRW_parser-0.1.4.dist-info/entry_points.txt
SRW_parser-0.1.4.dist-info/top_level.txt
parse_and_visualize/__init__.py
parse_and_visualize/_version.py
parse_and_visualize/parse_and_visualize.py
